puredata_compiler/__init__.py
puredata_compiler/api.py
puredata_compiler-0.0.1.dist-info/METADATA
puredata_compiler-0.0.1.dist-info/WHEEL
puredata_compiler-0.0.1.dist-info/top_level.txt
puredata_compiler-0.0.1.dist-info/RECORD
