Metadata-Version: 2.1
Name: puredata-compiler
Version: 0.0.1
Summary: A tool for writing PureData patches
Home-page: https://github.com/dylanburati/puredata-compiler
Author: Dylan Burati
Author-email: dylanburati@protonmail.com
License: UNKNOWN
Platform: UNKNOWN
Classifier: Programming Language :: Python :: 3.6
Classifier: Programming Language :: Python :: 3.7
Classifier: Programming Language :: Python :: 3.8
Classifier: License :: OSI Approved :: MIT License
Classifier: Operating System :: OS Independent
Classifier: Topic :: Multimedia :: Sound/Audio
